testmcpy/__init__.py
testmcpy/auth_debugger.py
testmcpy/auth_flow_recorder.py
testmcpy/config.py
testmcpy/error_handlers.py
testmcpy/llm_profiles.py
testmcpy/mcp_profiles.py
testmcpy/smoke_test.py
testmcpy/storage.py
testmcpy/test_profiles.py
testmcpy/cli/__init__.py
testmcpy/cli/app.py
testmcpy/cli/commands/__init__.py
testmcpy/cli/commands/mcp.py
testmcpy/cli/commands/run.py
testmcpy/cli/commands/server.py
testmcpy/cli/commands/tools.py
testmcpy/cli/commands/tui.py
testmcpy/core/__init__.py
testmcpy/core/chat_session.py
testmcpy/core/docs_optimizer.py
testmcpy/core/mcp_manager.py
testmcpy/core/tool_comparison.py
testmcpy/core/tool_discovery.py
testmcpy/evals/__init__.py
testmcpy/evals/auth_evaluators.py
testmcpy/evals/base_evaluators.py
testmcpy/formatters/__init__.py
testmcpy/formatters/base.py
testmcpy/formatters/curl.py
testmcpy/formatters/graphql.py
testmcpy/formatters/javascript_client.py
testmcpy/formatters/json_yaml.py
testmcpy/formatters/protobuf.py
testmcpy/formatters/python.py
testmcpy/formatters/python_client.py
testmcpy/formatters/thrift.py
testmcpy/formatters/typescript.py
testmcpy/formatters/typescript_client.py
testmcpy/research/claude_sdk_detailed_exploration.py
testmcpy/research/claude_sdk_poc.py
testmcpy/research/claude_sdk_working_poc.py
testmcpy/research/test_ollama_tools.py
testmcpy/server/__init__.py
testmcpy/server/api.py
testmcpy/server/api.py.bak
testmcpy/server/models.py
testmcpy/server/state.py
testmcpy/server/websocket.py
testmcpy/server/helpers/__init__.py
testmcpy/server/helpers/mcp_config.py
testmcpy/server/routers/__init__.py
testmcpy/server/routers/auth.py
testmcpy/server/routers/generation_logs.py
testmcpy/server/routers/llm.py
testmcpy/server/routers/mcp_profiles.py
testmcpy/server/routers/results.py
testmcpy/server/routers/smoke_reports.py
testmcpy/server/routers/test_profiles.py
testmcpy/server/routers/tests.py
testmcpy/server/routers/tools.py
testmcpy/src/__init__.py
testmcpy/src/llm_integration.py
testmcpy/src/mcp_client.py
testmcpy-0.2.17.dist-info/licenses/LICENSE
testmcpy-0.2.17.dist-info/licenses/NOTICE
testmcpy-0.2.17.dist-info/METADATA
testmcpy-0.2.17.dist-info/WHEEL
testmcpy-0.2.17.dist-info/entry_points.txt
testmcpy-0.2.17.dist-info/top_level.txt
testmcpy-0.2.17.dist-info/RECORD
