Metadata-Version: 2.4
Name: testmcpy
Version: 0.2.17
Summary: A comprehensive testing framework for validating LLM tool calling capabilities with MCP services
Author: Amin Ghadersohi
License-Expression: Apache-2.0
Project-URL: Homepage, https://github.com/preset-io/testmcpy
Project-URL: Repository, https://github.com/preset-io/testmcpy
Project-URL: Issues, https://github.com/preset-io/testmcpy/issues
Classifier: Development Status :: 4 - Beta
Classifier: Intended Audience :: Developers
Classifier: Programming Language :: Python :: 3
Classifier: Programming Language :: Python :: 3.10
Classifier: Programming Language :: Python :: 3.11
Classifier: Programming Language :: Python :: 3.12
Requires-Python: <3.13,>=3.10
License-File: LICENSE
License-File: NOTICE
Requires-Dist: typer<1.0.0,>=0.9.0
Requires-Dist: rich<15.0.0,>=13.0.0
Requires-Dist: pyyaml<7.0,>=6.0
Requires-Dist: requests<3.0.0,>=2.28.0
Requires-Dist: aiohttp<4.0.0,>=3.8.0
Requires-Dist: ollama>=0.1.0
Requires-Dist: anthropic<1.0.0,>=0.39.0
Requires-Dist: fastmcp<3.0.0,>=2.0.0
Requires-Dist: httpx<1.0.0,>=0.27.0
Requires-Dist: python-dotenv<2.0.0,>=1.0.0
Requires-Dist: click<9.0.0,>=8.0.0
Requires-Dist: shellingham<2.0.0,>=1.3.0
Requires-Dist: textual<1.0.0,>=0.47.0
Provides-Extra: dev
Requires-Dist: ruff>=0.8.0; extra == "dev"
Requires-Dist: mypy>=1.13.0; extra == "dev"
Requires-Dist: pytest>=7.0.0; extra == "dev"
Requires-Dist: pytest-cov>=4.0.0; extra == "dev"
Requires-Dist: pytest-asyncio>=0.21.0; extra == "dev"
Requires-Dist: pre-commit>=3.0.0; extra == "dev"
Requires-Dist: build>=1.0.0; extra == "dev"
Requires-Dist: twine>=5.0.0; extra == "dev"
Requires-Dist: types-pyyaml>=6.0.0; extra == "dev"
Requires-Dist: types-requests>=2.28.0; extra == "dev"
Requires-Dist: textual-dev>=1.0.0; extra == "dev"
Provides-Extra: server
Requires-Dist: fastapi<1.0.0,>=0.104.0; extra == "server"
Requires-Dist: uvicorn[standard]<1.0.0,>=0.24.0; extra == "server"
Requires-Dist: websockets<15.0,>=14.0; extra == "server"
Provides-Extra: sdk
Requires-Dist: claude-agent-sdk>=0.1.0; extra == "sdk"
Provides-Extra: tui
Requires-Dist: textual>=0.85.0; extra == "tui"
Provides-Extra: all
Requires-Dist: fastapi<1.0.0,>=0.104.0; extra == "all"
Requires-Dist: uvicorn[standard]<1.0.0,>=0.24.0; extra == "all"
Requires-Dist: websockets<15.0,>=14.0; extra == "all"
Requires-Dist: claude-agent-sdk>=0.1.0; extra == "all"
Requires-Dist: textual>=0.85.0; extra == "all"
Dynamic: license-file
